Workbook

Sheet Cover
A2: PERSONAL INVESTMENT PORTFOLIO TRACKER
A3: Demo Portfolio — For Project Demonstration Purposes
A4: April 2024 – March 2025 (FY2025)
A6: Prepared by: Tharineesh M
A7: B.Com (Final Year) | SAP S/4HANA Certified Associate
A9: Note: This is a demo portfolio created for project demonstration.
A10: All prices are sourced from NSE India historical data / market history pages.
A12: Contents:
A13: 1. Portfolio_Input — Raw input data and purchase details
A14: 2. Price_Reference — Current price lookup table
A15: 3. Portfolio_Calc — Formula-driven calculations
A16: 4. Dashboard — Visual summary and KPI cards
... A19: 7. Methodology — Assumptions, update steps, and sources

Sheet Portfolio_Input
A1: Stock Name | B1: Ticker | C1: Sector | D1: Quantity | E1: Buy Price (₹) | F1: Buy Date | G1: Exchange | H1: Notes
A2: Infosys Ltd | B2: INFY | C2: IT Services | D2: 10 | E2: 1495.45 | F2: 45383 | G2: NSE | H2: Initial demo purchase
A3: HDFC Bank | B3: HDFCBANK | C3: Banking | D3: 8 | E3: 735.25 | F3: 45383 | G3: NSE | H3: Initial demo purchase
A4: Reliance Industries | B4: RELIANCE | C4: Conglomerate | D4: 5 | E4: 1484.78 | F4: 45383 | G4: NSE | H4: Initial demo purchase
A5: TCS Ltd | B5: TCS | C5: IT Services | D5: 6 | E5: 3916.75 | F5: 45383 | G5: NSE | H5: Initial demo purchase
A6: Asian Paints | B6: ASIANPAINT | C6: Consumer | D6: 9 | E6: 2871 | F6: 45383 | G6: NSE | H6: Initial demo purchase
A7: Maruti Suzuki | B7: MARUTI | C7: Auto | D7: 2 | E7: 12569.6 | F7: 45383 | G7: NSE | H7: Initial demo purchase
A8: Sun Pharma | B8: SUNPHARMA | C8: Healthcare | D8: 15 | E8: 1629.25 | F8: 45383 | G8: NSE | H8: Initial demo purchase
A9: ITC Ltd | B9: ITC | C9: FMCG | D9: 50 | E9: 403.66 | F9: 45383 | G9: NSE | H9: Initial demo purchase
A11: Row 11: Data Source: NSE India Historical Data / market history pages
A12: Row 12: Buy prices represent closing prices on April 1, 2024
A13: Row 13: This is a DEMO portfolio for project demonstration purposes

Sheet Price_Reference
A1: Ticker | B1: Current Price (₹) | C1: As of Date
A2: INFY | B2: 1526.5 | C2: 45748
A3: HDFCBANK | B3: 883.93 | C3: 45748
A4: RELIANCE | B4: 1252.6 | C4: 45748
A5: TCS | B5: 3550.8 | C5: 45748
A6: ASIANPAINT | B6: 2316 | C6: 45748
A7: MARUTI | B7: 11481.1 | C7: 45748
A8: SUNPHARMA | B8: 1698.35 | C8: 45748
A9: ITC | B9: 406.65 | C9: 45748
A12: Source: EquityPandit historical data pages (April 2025 row used for FY2025 end-period reference)
A13: Note: Replace Column B values with updated market prices to refresh the tracker.
A14: All calculations in Portfolio_Calc update automatically.

Sheet Portfolio_Calc
A1: Stock Name | B1: Ticker | C1: Sector | D1: Quantity | E1: Buy Price (₹) | F1: Current Price (₹) | G1: Investment Value (₹) | H1: Current Value (₹) | I1: Absolute Gain/Loss (₹) | J1: Gain/Loss % | K1: Portfolio Weight % | L1: Status
A2: =Portfolio_Input!A2 | B2: =Portfolio_Input!B2 | C2: =Portfolio_Input!C2 | D2: =Portfolio_Input!D2 | E2: =Portfolio_Input!E2 | F2: =VLOOKUP(B2,Price_Reference!$A:$B,2,0) | G2: =D2*E2 | H2: =D2*F2 | I2: =H2-G2 | J2: =(H2-G2)/G2 | K2: =G2/SUM($G$2:$G$9) | L2: =IF(I2>0,"PROFIT","LOSS")
A3: =Portfolio_Input!A3 | B3: =Portfolio_Input!B3 | C3: =Portfolio_Input!C3 | D3: =Portfolio_Input!D3 | E3: =Portfolio_Input!E3 | F3: =VLOOKUP(B3,Price_Reference!$A:$B,2,0) | G3: =D3*E3 | H3: =D3*F3 | I3: =H3-G3 | J3: =(H3-G3)/G3 | K3: =G3/SUM($G$2:$G$9) | L3: =IF(I3>0,"PROFIT","LOSS")
A4: =Portfolio_Input!A4 | B4: =Portfolio_Input!B4 | C4: =Portfolio_Input!C4 | D4: =Portfolio_Input!D4 | E4: =Portfolio_Input!E4 | F4: =VLOOKUP(B4,Price_Reference!$A:$B,2,0) | G4: =D4*E4 | H4: =D4*F4 | I4: =H4-G4 | J4: =(H4-G4)/G4 | K4: =G4/SUM($G$2:$G$9) | L4: =IF(I4>0,"PROFIT","LOSS")
A5: =Portfolio_Input!A5 | B5: =Portfolio_Input!B5 | C5: =Portfolio_Input!C5 | D5: =Portfolio_Input!D5 | E5: =Portfolio_Input!E5 | F5: =VLOOKUP(B5,Price_Reference!$A:$B,2,0) | G5: =D5*E5 | H5: =D5*F5 | I5: =H5-G5 | J5: =(H5-G5)/G5 | K5: =G5/SUM($G$2:$G$9) | L5: =IF(I5>0,"PROFIT","LOSS")
A6: =Portfolio_Input!A6 | B6: =Portfolio_Input!B6 | C6: =Portfolio_Input!C6 | D6: =Portfolio_Input!D6 | E6: =Portfolio_Input!E6 | F6: =VLOOKUP(B6,Price_Reference!$A:$B,2,0) | G6: =D6*E6 | H6: =D6*F6 | I6: =H6-G6 | J6: =(H6-G6)/G6 | K6: =G6/SUM($G$2:$G$9) | L6: =IF(I6>0,"PROFIT","LOSS")
A7: =Portfolio_Input!A7 | B7: =Portfolio_Input!B7 | C7: =Portfolio_Input!C7 | D7: =Portfolio_Input!D7 | E7: =Portfolio_Input!E7 | F7: =VLOOKUP(B7,Price_Reference!$A:$B,2,0) | G7: =D7*E7 | H7: =D7*F7 | I7: =H7-G7 | J7: =(H7-G7)/G7 | K7: =G7/SUM($G$2:$G$9) | L7: =IF(I7>0,"PROFIT","LOSS")
A8: =Portfolio_Input!A8 | B8: =Portfolio_Input!B8 | C8: =Portfolio_Input!C8 | D8: =Portfolio_Input!D8 | E8: =Portfolio_Input!E8 | F8: =VLOOKUP(B8,Price_Reference!$A:$B,2,0) | G8: =D8*E8 | H8: =D8*F8 | I8: =H8-G8 | J8: =(H8-G8)/G8 | K8: =G8/SUM($G$2:$G$9) | L8: =IF(I8>0,"PROFIT","LOSS")
A9: =Portfolio_Input!A9 | B9: =Portfolio_Input!B9 | C9: =Portfolio_Input!C9 | D9: =Portfolio_Input!D9 | E9: =Portfolio_Input!E9 | F9: =VLOOKUP(B9,Price_Reference!$A:$B,2,0) | G9: =D9*E9 | H9: =D9*F9 | I9: =H9-G9 | J9: =(H9-G9)/G9 | K9: =G9/SUM($G$2:$G$9) | L9: =IF(I9>0,"PROFIT","LOSS")
A10: TOTAL | G10: =SUM(G2:G9) | H10: =SUM(H2:H9) | I10: =SUM(I2:I9) | J10: =(H10-G10)/G10 | K10: =SUM(K2:K9)

Sheet Dashboard
A1: PORTFOLIO DASHBOARD — THARINEESH M (DEMO)
J2: Best Performer
J3: =INDEX(Portfolio_Calc!A$2:A$9,MATCH(MAX(Portfolio_Calc!J$2:J$9),Portfolio_Calc!J$2:J$9,0))
A4: Total Invested | C4: Current Value | E4: Total G/L | G4: Return % | J4: Best Return %
A5: =Portfolio_Calc!G10 | C5: =Portfolio_Calc!H10 | E5: =Portfolio_Calc!I10 | G5: =Portfolio_Calc!J10 | J5: =MAX(Portfolio_Calc!J2:J9)
J6: Worst Performer
J7: =INDEX(Portfolio_Calc!A$2:A$9,MATCH(MIN(Portfolio_Calc!J$2:J$9),Portfolio_Calc!J$2:J$9,0))
J8: Worst Return %
J9: =MIN(Portfolio_Calc!J2:J9)
J10: Average Return
J11: =AVERAGE(Portfolio_Calc!J2:J9)
J30: Sector | K30: Investment Value
J31: IT Services | K31: =SUMIF(Portfolio_Calc!C:C,"IT Services",Portfolio_Calc!G:G)
J32: Banking | K32: =SUMIF(Portfolio_Calc!C:C,"Banking",Portfolio_Calc!G:G)
J33: Conglomerate | K33: =SUMIF(Portfolio_Calc!C:C,"Conglomerate",Portfolio_Calc!G:G)
J34: Consumer | K34: =SUMIF(Portfolio_Calc!C:C,"Consumer",Portfolio_Calc!G:G)
J35: Auto | K35: =SUMIF(Portfolio_Calc!C:C,"Auto",Portfolio_Calc!G:G)
J36: Healthcare | K36: =SUMIF(Portfolio_Calc!C:C,"Healthcare",Portfolio_Calc!G:G)
J37: FMCG | K37: =SUMIF(Portfolio_Calc!C:C,"FMCG",Portfolio_Calc!G:G)

Sheet Transactions
A1: Date | B1: Stock | C1: Ticker | D1: Action | E1: Quantity | F1: Price (₹) | G1: Value (₹) | H1: Notes
A2: 45383 | B2: Infosys Ltd | C2: INFY | D2: BUY | E2: 10 | F2: 1495.45 | G2: =E2*F2 | H2: Initial purchase
A3: 45383 | B3: HDFC Bank | C3: HDFCBANK | D3: BUY | E3: 8 | F3: 735.25 | G3: =E3*F3 | H3: Initial purchase
A4: 45383 | B4: Reliance Industries | C4: RELIANCE | D4: BUY | E4: 5 | F4: 1484.78 | G4: =E4*F4 | H4: Initial purchase
A5: 45383 | B5: TCS Ltd | C5: TCS | D5: BUY | E5: 6 | F5: 3916.75 | G5: =E5*F5 | H5: Initial purchase
A6: 45383 | B6: Asian Paints | C6: ASIANPAINT | D6: BUY | E6: 9 | F6: 2871 | G6: =E6*F6 | H6: Initial purchase
A7: 45383 | B7: Maruti Suzuki | C7: MARUTI | D7: BUY | E7: 2 | F7: 12569.6 | G7: =E7*F7 | H7: Initial purchase
A8: 45383 | B8: Sun Pharma | C8: SUNPHARMA | D8: BUY | E8: 15 | F8: 1629.25 | G8: =E8*F8 | H8: Initial purchase
A9: 45383 | B9: ITC Ltd | C9: ITC | D9: BUY | E9: 50 | F9: 403.66 | G9: =E9*F9 | H9: Initial purchase
A10: Total Capital Deployed | G10: =SUM(G2:G9)

Sheet Summary
A1: PORTFOLIO SUMMARY — DEMO PORTFOLIO (FY2025)
A2: Prepared by: Tharineesh M
A3: Period: April 1, 2024 – March 31, 2025
A4: Total Holdings: 8 stocks across 5 sectors
A6: PERFORMANCE OVERVIEW
A7: Total Investment | B7: =Portfolio_Calc!G10
A8: Current Value | B8: =Portfolio_Calc!H10
A9: Absolute Return (₹) | B9: =Portfolio_Calc!I10
A10: Return (%) | B10: =Portfolio_Calc!J10
A12: BEST AND WORST PERFORMERS
A13: Best Stock | B13: =INDEX(Portfolio_Calc!A$2:A$9,MATCH(MAX(Portfolio_Calc!J$2:J$9),Portfolio_Calc!J$2:J$9,0))
A14: Worst Stock | B14: =INDEX(Portfolio_Calc!A$2:A$9,MATCH(MIN(Portfolio_Calc!J$2:J$9),Portfolio_Calc!J$2:J$9,0))
A15: Average Return | B15: =AVERAGE(Portfolio_Calc!J2:J9)
A17: SECTOR EXPOSURE
A18: IT Services | B18: =Dashboard!K31
A19: Banking | B19: =Dashboard!K32
A20: Conglomerate | B20: =Dashboard!K33
A21: Consumer | B21: =Dashboard!K34
A22: Auto | B22: =Dashboard!K35
A23: Healthcare | B23: =Dashboard!K36
A24: FMCG | B24: =Dashboard!K37
A27: NOTE: This is a demo portfolio built for project demonstration.
A28: All prices sourced from historical market data pages.

Sheet Methodology
A1: METHODOLOGY NOTES
A3: 1. PRICE DATA Buy prices represent the closing price of each stock on April 1, 2024, sourced from historical data pages. Current prices represent closing prices on April 1, 2025, sourced from the same pages.
A6: 2. PORTFOLIO CONSTRUCTION This is a demo portfolio constructed to demonstrate Excel-based portfolio tracking, formula logic, and financial analysis skills. Holdings and quantities were selected to represent a diversified portfolio across 5 sectors.
A9: 3. FORMULA LOGIC - Current prices are fetched dynamically from Price_Reference using VLOOKUP - Portfolio weights use absolute references to ensure accurate percentage calculation - Sector allocation uses SUMIF to aggregate investment by sector - Best/Worst performer identification uses INDEX-MATCH combination
A12: 4. HOW TO UPDATE Step 1: Open the Price_Reference sheet Step 2: Update Column B values with new market prices Step 3: All Portfolio_Calc and Dashboard calculations update automatically Step 4: No other changes needed
A15: 5. FORMULAS USED - VLOOKUP: Dynamic price lookup from reference table - SUMIF: Sector-wise investment aggregation - INDEX-MATCH: Best and worst performer identification - IF with Conditional Formatting: Profit/Loss status - SUM, AVERAGE, MAX, MIN: Portfolio-level aggregation
A18: 6. LIMITATIONS - Does not account for brokerage fees or transaction costs - Does not account for dividends received during the period - Prices are end-of-day historical prices, not intraday
